odoo/addons/stock_measuring_device_zippcube/README.rst
odoo/addons/stock_measuring_device_zippcube/__init__.py
odoo/addons/stock_measuring_device_zippcube/__manifest__.py
odoo/addons/stock_measuring_device_zippcube/components/__init__.py
odoo/addons/stock_measuring_device_zippcube/components/zippcube_device_component.py
odoo/addons/stock_measuring_device_zippcube/controllers/__init__.py
odoo/addons/stock_measuring_device_zippcube/controllers/main.py
odoo/addons/stock_measuring_device_zippcube/i18n/it.po
odoo/addons/stock_measuring_device_zippcube/i18n/stock_measuring_device_zippcube.pot
odoo/addons/stock_measuring_device_zippcube/models/__init__.py
odoo/addons/stock_measuring_device_zippcube/models/measuring_device.py
odoo/addons/stock_measuring_device_zippcube/readme/CONFIGURE.md
odoo/addons/stock_measuring_device_zippcube/readme/CONTRIBUTORS.md
odoo/addons/stock_measuring_device_zippcube/readme/CREDITS.md
odoo/addons/stock_measuring_device_zippcube/readme/DESCRIPTION.md
odoo/addons/stock_measuring_device_zippcube/readme/INSTALL.md
odoo/addons/stock_measuring_device_zippcube/readme/ROADMAP.md
odoo/addons/stock_measuring_device_zippcube/readme/USAGE.md
odoo/addons/stock_measuring_device_zippcube/scripts/measurement.sh
odoo/addons/stock_measuring_device_zippcube/static/description/icon.png
odoo/addons/stock_measuring_device_zippcube/static/description/index.html
odoo/addons/stock_measuring_device_zippcube/tests/__init__.py
odoo/addons/stock_measuring_device_zippcube/tests/test_zippcube_wizard.py
odoo_addon_stock_measuring_device_zippcube-18.0.1.0.0.2.dist-info/METADATA
odoo_addon_stock_measuring_device_zippcube-18.0.1.0.0.2.dist-info/WHEEL
odoo_addon_stock_measuring_device_zippcube-18.0.1.0.0.2.dist-info/top_level.txt
odoo_addon_stock_measuring_device_zippcube-18.0.1.0.0.2.dist-info/RECORD
